{
  "report_date": "2026-05-02",
  "generated_at": "2026-05-02T18:09:49",
  "period": "증분 수집 기준 시각부터 현재까지",
  "count": 3,
  "items": [
    {
      "id": "video-4",
      "youtuber": "사또의 경제 이야기",
      "headline": "개인 투자자가 자산을 잃는 4가지 치명적인 투자 습관",
      "video_published_at": "2026-05-02T08:36:02+09:00",
      "video_published_display": "2026-05-02 08:36",
      "published_at_source": "rss",
      "source_url": "https://www.youtube.com/watch?v=qiGXD7GAGNw",
      "original_title": "주식 투자할수록 돈을 잃는 사람들의 공통점 4가지 | 90%가 빠지는 투자 습관의 함정",
      "summary": "[헤드라인]\n\n개인 투자자가 자산을 잃는 4가지 치명적인 투자 습관\n\n[리드]\n\n'사또의 경제 이야기'는 많은 개인 투자자가 반복하는 잘못된 투자 습관을 분석하고, 감정에 휘둘리지 않는 체계적인 투자 원칙의 중요성을 강조합니다.\n\n[핵심 뉴스]\n\n- 불분명한 매수 이유: 추천이나 소문에 의존해 매수 이유를 한 줄로 정리하지 못하는 것은 투자가 아닌 도박과 같습니다 (01:28-03:28).\n- 매도 기준 부재: 욕심과 두려움으로 인해 손절과 익절 타이밍을 놓쳐 단기 투자가 강제 장기 투자가 되는 악순환을 경계해야 합니다 (03:31-06:31).\n- 레버리지의 위험성: 빚을 내거나 고위험 상품으로 단기간에 부를 이루려는 시도는 자산을 빠르게 녹이는 지름길입니다 (06:33-08:48).\n- 시장 반대 베팅의 함정: 인버스나 곱버스 상품은 '음의 복리' 구조를 가져 장기 보유 시 자산 가치가 하락할 위험이 큽니다 (08:50-11:43).\n- 세 줄 처방: 매수 전 '매수 이유', '익절가', '손절가'를 반드시 기록하여 객관적인 기준을 세워야 합니다 (12:34-13:00).\n\n[시장 시사점]\n\n- 자기 통제: 시장 분석력보다 자신의 욕심과 두려움을 통제하는 자기 조절 능력이 수익률에 더 큰 영향을 미칩니다 (13:00-13:20).\n- 부의 본질: 부의 축적은 '시간'과 '복리'를 통해 이루어지는 것이며, 한 방을 노리는 행위는 자산을 잃는 지름길입니다 (06:45-07:20).\n\n[유의점]\n\n- 심리적 요인: 시장이 비합리적인 구간을 길게 유지할 경우, 투자자가 준비한 기준이 무력화될 수 있으므로 끊임없는 심리적 통제가 전제되어야 합니다 (11:06-11:43).\n- 개별 판단의 책임: 영상에서 제시하는 처방은 정보 제공 목적이며, 모든 최종 투자 판단과 책임은 투자자 본인에게 있습니다.",
      "summary_provider": "gemini"
    },
    {
      "id": "video-6",
      "youtuber": "전인구경제연구소",
      "headline": "투자 고수들의 6가지 실전 투자 기법 및 시장 대응 전략",
      "video_published_at": "2026-05-01T18:27:46+09:00",
      "video_published_display": "2026-05-01 18:27",
      "published_at_source": "rss",
      "source_url": "https://www.youtube.com/watch?v=0XQsqOIZc_Q",
      "original_title": "주식투자 하루 만에 끝내기 7탄 고수들 주식투자 기술 몰아보기",
      "summary": "[헤드라인]\n\n투자 고수들의 6가지 실전 투자 기법 및 시장 대응 전략\n\n[리드]\n\n이 영상은 외국인·기관 수급, 사모펀드 투자, 이모작 전략 등 다양한 투자 고수들의 기법을 소개합니다. 투자는 정해진 공식보다 시장 상황에 맞는 유연한 플레이가 중요하며, 각 기법의 원리와 한계를 이해하고 적용해야 함을 강조합니다.\n\n[핵심 뉴스]\n\n- 수급 분석: 외국인이나 기관이 3~5일 연속 매수세를 보일 때가 투자 판단의 기회가 될 수 있으나, 무조건적 추종보다는 매수 이유를 분석해야 함 (01:28 - 04:51)\n- 사모펀드 투자: 사모펀드가 인수한 기업은 비용 절감 및 경영 효율화를 통해 가치를 높여 매각하려는 목적이 크므로, 이들의 행보를 주목할 가치가 있음 (04:56 - 12:27)\n- 이모작 투자: 특정 산업의 상승 사이클을 활용해 시간차를 두고 연관된 산업(예: 조선-엔진, 전기차-타이어)에 순차적으로 투자하는 방식임 (12:28 - 17:19)\n- 역발상 투자: 시장에서 버림받은 업종이 공급 과잉 해소와 치킨 게임을 거쳐 다시 초호황을 맞이하는 사이클을 이용하는 기법임 (17:19 - 22:30)\n- 블루칩 vs 옐로칩: 안정성을 중시한다면 블루칩, 상승기 수익 극대화를 노린다면 옐로칩을 선택하되 초보자는 안정적인 블루칩 투자가 적합함 (22:31 - 25:51)\n\n[시장 시사점]\n\n- 배당 성장주 주목: 배당 수익률이 비정상적으로 높은 주식(6% 이상)보다는 배당금이 매년 꾸준히 성장하는 기업을 찾아 장기 투자하는 것이 유리함 (25:52 - 28:40)\n- 하락장 대응 전략: 하락기에는 공매도, 인버스 ETF, 선물 옵션 등을 통해 위험을 관리하거나 수익을 추구하는 방법을 활용할 수 있음 (28:41 - 31:42)\n\n[유의점]\n\n- 모든 기법은 100% 성공을 보장하지 않으므로 상황 변화에 따른 유연한 타격폼 수정(전략 변경)이 필수적임 (00:04 - 00:48)\n- 배당 수익률이 6~7%를 넘어서는 경우, 주가 하락이 동반될 가능성이 높으므로 기업의 펀더멘털을 반드시 확인해야 함 (26:00 - 26:55)",
      "summary_provider": "gemini"
    },
    {
      "id": "video-9",
      "youtuber": "전인구경제연구소",
      "headline": "성공적인 공모주 투자와 효율적인 절세 계좌 운용 전략",
      "video_published_at": "2026-05-01T11:08:09+09:00",
      "video_published_display": "2026-05-01 11:08",
      "published_at_source": "rss",
      "source_url": "https://www.youtube.com/watch?v=in_uURDBKic",
      "original_title": "공모주 투자 이것만 확인하세요(ft.요니나 작가 2부)",
      "summary": "[헤드라인]\n\n성공적인 공모주 투자와 효율적인 절세 계좌 운용 전략\n\n[리드]\n\n본 영상은 요니나 작가와 함께 안전자산 확보의 중요성부터 공모주 투자 시 확인해야 할 핵심 지표 및 절세 계좌 활용법을 다룹니다. 초보 투자자가 시장 상황에 흔들리지 않고 장기적인 수익을 창출하기 위한 실질적인 가이드를 제시합니다.\n\n[핵심 뉴스]\n\n- ETF 투자는 대표 지수(S&P 500, 나스닥 100 등)를 추종하고 적립식 매수를 활용하여 매수 단가를 평준화하는 것이 효과적입니다.\n- 공모주 청약 시 기관 경쟁률과 참여 기관 수, 의무 보유 확약 비율을 통해 기업의 가치를 사전 분석해야 합니다.\n- 공모주는 상장 직후 변동성이 크므로, 적정 수준에서 익절을 실현하고 하락세 시에는 빠르게 손절하는 원칙이 필요합니다.\n- ISA, 연금저축펀드, IRP 등 절세 3종 세트를 활용하여 투자 종목의 성격에 맞는 세제 혜택을 극대화해야 합니다.\n\n[시장 시사점]\n\n- 시장 상황이 좋을 때 저축을 소홀히 하기보다, 하락장을 견딜 수 있는 일정 수준의 현금성 안전자산을 반드시 보유해야 합니다.\n- 공모주는 '묻지마 청약'이 아닌, 다트(DART) 등을 통해 유통 물량 및 기관 확약을 확인하는 체계적인 접근이 성공 확률을 높입니다.\n\n[유의점]\n\n- 공모주 청약 시 발생하는 수수료와 증권사별 계좌 개설 제한(20 영업일) 등 제반 조건을 미리 고려해야 합니다.\n- 투자 설명서상 공모가 밴드 하단에 수요가 몰리는 기업은 상장 후 주가 흐름이 부정적일 수 있으므로 주의가 필요합니다.",
      "summary_provider": "gemini"
    }
  ]
}
