{
  "marketStatus": "한국장 개장 전",
  "currentTimeKst": "2026-04-08T02:07:04.157262+09:00",
  "predictionDate": "2026-04-09",
  "rangeLow": 5415,
  "rangeHigh": 5481,
  "pointPrediction": 5448,
  "predictedChangePct": -0.04,
  "confidence": 4,
  "confidenceLabel": "높음",
  "signalSummary": "S&P500 약세, 필라델피아반도체 강세",
  "lastCalculatedAt": "2026-04-08T02:07:04.157262+09:00",
  "bandHitRate30d": 40.0,
  "directionHitRate30d": 80.0,
  "mae30d": 83.29,
  "yesterday": {
    "predictionLow": 5178.9,
    "predictionHigh": 5328.72,
    "actualOpen": 5375.5,
    "hit": false
  },
  "model": {
    "modelA": 5448.02,
    "modelB": 5442.84,
    "divergencePct": 0.1,
    "bandMultiplier": 1.5,
    "vix": 26.21,
    "selectedFeatures": [
      "sp500_return",
      "sox_return"
    ]
  }
}