{
  "summary": {
    "mae30d": 18.12
  },
  "records": [
    { "date": "2026-04-07", "low": 5434.42, "high": 5488.78, "actualOpen": 5441.0, "hit": true },
    { "date": "2026-04-06", "low": 5348.22, "high": 5400.06, "actualOpen": 5423.35, "hit": false },
    { "date": "2026-04-03", "low": 5208.94, "high": 5255.48, "actualOpen": 5375.5, "hit": false },
    { "date": "2026-04-02", "low": 5499.19, "high": 5541.92, "actualOpen": 5551.69, "hit": false },
    { "date": "2026-04-01", "low": 5092.44, "high": 5167.92, "actualOpen": 5330.04, "hit": false },
    { "date": "2026-03-31", "low": 5213.43, "high": 5276.76, "actualOpen": 5143.75, "hit": false },
    { "date": "2026-03-30", "low": 5388.66, "high": 5463.44, "actualOpen": 5181.8, "hit": false },
    { "date": "2026-03-27", "low": 5344.83, "high": 5411.56, "actualOpen": 5300.61, "hit": false },
    { "date": "2026-03-26", "low": 5654.54, "high": 5705.32, "actualOpen": 5594.06, "hit": false },
    { "date": "2026-03-25", "low": 5555.03, "high": 5605.01, "actualOpen": 5680.33, "hit": false },
    { "date": "2026-03-24", "low": 5384.62, "high": 5433.27, "actualOpen": 5638.2, "hit": false },
    { "date": "2026-03-23", "low": 5713.81, "high": 5776.91, "actualOpen": 5580.15, "hit": false },
    { "date": "2026-03-20", "low": 5734.11, "high": 5779.06, "actualOpen": 5813.35, "hit": false },
    { "date": "2026-03-19", "low": 5859.26, "high": 5918.13, "actualOpen": 5761.4, "hit": false },
    { "date": "2026-03-18", "low": 5616.63, "high": 5660.62, "actualOpen": 5767.1, "hit": false },
    { "date": "2026-03-17", "low": 5564.42, "high": 5607.71, "actualOpen": 5711.8, "hit": false },
    { "date": "2026-03-16", "low": 5450.01, "high": 5499.4, "actualOpen": 5510.82, "hit": false },
    { "date": "2026-03-13", "low": 5495.86, "high": 5579.39, "actualOpen": 5412.39, "hit": false },
    { "date": "2026-03-12", "low": 5597.52, "high": 5641.27, "actualOpen": 5567.65, "hit": false },
    { "date": "2026-03-11", "low": 5505.73, "high": 5570.68, "actualOpen": 5658.72, "hit": false },
    { "date": "2026-03-10", "low": 5263.44, "high": 5310.7, "actualOpen": 5523.21, "hit": false },
    { "date": "2026-03-09", "low": 5544.72, "high": 5617.38, "actualOpen": 5265.37, "hit": false },
    { "date": "2026-03-06", "low": 5480.12, "high": 5530.50, "actualOpen": 5545.10, "hit": false },
    { "date": "2026-03-05", "low": 5610.33, "high": 5660.20, "actualOpen": 5490.80, "hit": false },
    { "date": "2026-03-04", "low": 5520.40, "high": 5575.60, "actualOpen": 5612.30, "hit": false },
    { "date": "2026-03-03", "low": 5445.15, "high": 5500.85, "actualOpen": 5530.45, "hit": false },
    { "date": "2026-02-28", "low": 5390.20, "high": 5440.10, "actualOpen": 5458.90, "hit": false },
    { "date": "2026-02-27", "low": 5410.50, "high": 5465.30, "actualOpen": 5395.20, "hit": false },
    { "date": "2026-02-26", "low": 5350.80, "high": 5400.60, "actualOpen": 5415.10, "hit": false },
    { "date": "2026-02-25", "low": 5300.10, "high": 5355.90, "actualOpen": 5360.50, "hit": false }
  ]
}