{
  "primary": [
    {
      "key": "ewy",
      "label": "EWY (Korea ETF)",
      "value": "$139.04",
      "changePct": -0.74,
      "updatedAt": "2026-04-09T20:31:14+00:00",
      "sourceUrl": "https://finance.yahoo.com/quote/EWY",
      "dataSource": "Yahoo Finance",
      "displayTag": "",
      "isPremarket": false
    },
    {
      "key": "krw",
      "label": "USD/KRW",
      "value": "1,474.00원",
      "changePct": -1.68,
      "updatedAt": "2026-04-09T20:32:00+00:00",
      "sourceUrl": "https://finance.yahoo.com/quote/KRW%3DX",
      "dataSource": "Yahoo Finance",
      "displayTag": "",
      "isPremarket": false
    },
    {
      "key": "wti",
      "label": "WTI",
      "value": "$98.84",
      "changePct": 4.69,
      "updatedAt": "2026-04-09T20:22:00+00:00",
      "sourceUrl": "https://finance.yahoo.com/quote/CL%3DF",
      "dataSource": "Yahoo Finance",
      "displayTag": "",
      "isPremarket": false
    },
    {
      "key": "sp500",
      "label": "S&P 500",
      "value": "6,824.66",
      "changePct": 0.62,
      "updatedAt": "2026-04-09T20:19:00+00:00",
      "sourceUrl": "https://finance.yahoo.com/quote/%5EGSPC",
      "dataSource": "Yahoo Finance",
      "displayTag": "",
      "isPremarket": false
    }
  ],
  "secondary": [
    {
      "key": "nasdaq",
      "label": "NASDAQ 100",
      "value": "25,082.09",
      "changePct": 0.72,
      "updatedAt": "2026-04-09T20:31:00+00:00",
      "sourceUrl": "https://finance.yahoo.com/quote/%5ENDX",
      "dataSource": "Yahoo Finance",
      "displayTag": "",
      "isPremarket": false
    },
    {
      "key": "vix",
      "label": "VIX",
      "value": "19.48",
      "changePct": -7.41,
      "updatedAt": "2026-04-09T20:14:00+00:00",
      "sourceUrl": "https://finance.yahoo.com/quote/%5EVIX",
      "dataSource": "Yahoo Finance",
      "displayTag": "",
      "isPremarket": false
    },
    {
      "key": "koru",
      "label": "KORU 3x",
      "value": "$398.80",
      "changePct": -1.53,
      "updatedAt": "2026-04-09T20:32:04+00:00",
      "sourceUrl": "https://finance.yahoo.com/quote/KORU",
      "dataSource": "Yahoo Finance",
      "displayTag": "",
      "isPremarket": false
    },
    {
      "key": "k200f",
      "label": "KOSPI 200 야간선물",
      "value": "886.05",
      "changePct": 2.19,
      "updatedAt": "2026-04-09T20:32:35+00:00",
      "sourceUrl": "",
      "dataSource": "실시간 수집",
      "displayTag": "(야간)",
      "isPremarket": false,
      "referenceLabel": "주간선물 종가",
      "referenceValue": "867.05",
      "referenceDate": "2026-04-09"
    },
    {
      "key": "dow",
      "label": "Dow Jones",
      "value": "48,185.80",
      "changePct": 0.58,
      "updatedAt": "2026-04-09T20:19:00+00:00",
      "sourceUrl": "https://finance.yahoo.com/quote/%5EDJI",
      "dataSource": "Yahoo Finance",
      "displayTag": "",
      "isPremarket": false
    },
    {
      "key": "gold",
      "label": "Gold",
      "value": "$4,795.10",
      "changePct": 0.96,
      "updatedAt": "2026-04-09T20:22:00+00:00",
      "sourceUrl": "https://finance.yahoo.com/quote/GC%3DF",
      "dataSource": "Yahoo Finance",
      "displayTag": "",
      "isPremarket": false
    },
    {
      "key": "us10y",
      "label": "US 10Y",
      "value": "4.29%",
      "changePct": 0.05,
      "updatedAt": "2026-04-09T18:59:00+00:00",
      "sourceUrl": "https://finance.yahoo.com/quote/%5ETNX",
      "dataSource": "Yahoo Finance",
      "displayTag": "",
      "isPremarket": false
    },
    {
      "key": "sox",
      "label": "PHLX Semiconductor",
      "value": "8,689.53",
      "changePct": 2.1,
      "updatedAt": "2026-04-09T20:31:00+00:00",
      "sourceUrl": "https://finance.yahoo.com/quote/%5ESOX",
      "dataSource": "Yahoo Finance",
      "displayTag": "",
      "isPremarket": false
    }
  ],
  "generatedAt": "2026-04-09T20:32:47.508690+00:00",
  "isUsPremarketNow": false
}