{
  "generatedAt": "2026-04-09T14:32:50.609242+00:00",
  "records": [
    {
      "predictionDateIso": "2026-04-10",
      "predictionDate": "2026년 04월 10일",
      "generatedAt": "2026-04-09T14:32:50.608608+00:00",
      "rangeLow": 5744.34,
      "rangeHigh": 5793.21,
      "pointPrediction": 5768.77,
      "nightFuturesSimplePoint": 5762.71
    },
    {
      "predictionDateIso": "2026-04-09",
      "predictionDate": "2026년 04월 09일",
      "generatedAt": "2026-04-08T20:46:12.736641+00:00",
      "rangeLow": 5929.25,
      "rangeHigh": 5976.69,
      "pointPrediction": 5952.97,
      "nightFuturesSimplePoint": null
    }
  ]
}