{
  "generatedAt": "2026-04-09T03:10:48.478370+00:00",
  "predictionDate": "2026년 04월 10일",
  "pointPrediction": 5963.48,
  "nightFuturesSimplePoint": null,
  "nightFuturesSimpleChangePct": null,
  "futuresDayClose": 884.55,
  "futuresDayCloseDate": "2026-04-08",
  "rangeLow": 5939.76,
  "rangeHigh": 5987.2,
  "predictedChangePct": 1.55,
  "prevClose": 5872.34,
  "signalSummary": "EWY 상승 · S&P 500 상승 · VIX 하락(안정) · NASDAQ 100 상승 · USD/KRW 원화 강세",
  "lastCalculatedAt": "2026-04-09T03:10:48.478370+00:00",
  "latestRecordDate": "2026-04-08",
  "mae30d": 18.24,
  "model": {
    "engine": "LightGBM",
    "vix": 21.04,
    "lgbmRmse": 34.72,
    "calculationMode": "NightFuturesCore+AuxSignals",
    "nightFuturesAnchorPct": 1.15,
    "auxiliaryAnchorPct": 1.15,
    "coreAnchorPct": 1.15,
    "rawModelPct": 3.36,
    "mlResidualAdjPct": 0.4,
    "auxResidualAdjPct": 0.0,
    "prevCloseChangePct": 1.29
  },
  "yesterday": {
    "predictionLow": 5811.88,
    "predictionHigh": 5841.02,
    "actualOpen": 5826.45,
    "hit": true
  }
}